{
   "Name": "Charizma (band)",
   "rawData": [
      "Charizma is a Swedish rock band formed in Oskarshamn, Sweden. It was founded in 1981 by the three brothers Bo, Jan  and Göran Nikolausson. In 1996 the band added two members, Johan Mauritzson and Thomas Karlsson. In November 2008 the band went on an indefinite hiatus. \n",
      "Starting out as a hard rock trio in the early 1980's, at the end of the 1990's Charizma turned into a radio-friendly rock band focusing on melodies and strong vocal elements.\n",
      "The band is primarily known for its songs \"Waiting (Here for you)\" and \"Run to God\". The song \"Join hands\" (1990) was a major hit in Estonia and became part of the Singing Revolution. \n"
   ],
   "infobox": {
      "Origin": [
         "Oskarshamn, Sweden"
      ],
      "Genres": [
         "Rock, pop, CCM, hard rock"
      ],
      "Years active": [
         "1981 – Present (hiatus)"
      ],
      "Labels": [
         "Pama Records (SE), Talking Music (SE), Asaph Musik (D)"
      ],
      "Website": [
         "Charizma.com"
      ],
      "Members": [
         "Bo Nikolausson",
         "Jan Nikolausson",
         "Göran Nikolausson",
         "Johan Mauritzson",
         "Thomas (TK) Karlsson"
      ],
      "Past members": [
         "Mats Tärnfors",
         "Peter Koski"
      ]
   },
   "albums": []
}