{
   "Also known as": [
      "Kleenex"
   ],
   "Origin": [
      "Zürich, Switzerland"
   ],
   "Genres": [
      "Punk rockpost-punk[1]"
   ],
   "Years active": [
      "1978–1983"
   ],
   "Labels": [
      "SunriseRough TradeOff Course"
   ],
   "Past members": [
      "Lislot Ha",
      "Klaudia Schiff",
      "Regula Sing",
      "Rudolph Dietrich",
      "Gogi",
      "Marlene Marder",
      "Chrigle Freund",
      "Angie Barrack",
      "Christoph Herzog",
      "Beat Schlatter",
      "Astrid Spirit"
   ]
}