{
   "Origin": [
      "Gothenburg, Sweden"
   ],
   "Genres": [
      "Melodic death metal, industrial metal, alternative metal"
   ],
   "Years active": [
      "2005[1]–present"
   ],
   "Labels": [
      "Gain/Sony, Season of Mist, Trooper/Avex, Frostbyte"
   ],
   "Associated acts": [
      "Gardenian, Headplate, The Crown, Evergrey, In Flames, Passenger, Marionette, Degradead"
   ],
   "Website": [
      "Official site"
   ],
   "Members": [
      "Niclas EngelinMarcus SunessonSteve DrennanOscar NilssonMikael Sehlin"
   ]
}