{
   "Origin": [
      "Pittsburgh, Pennsylvania, United States"
   ],
   "Genres": [
      "Roots rock,[1] worldbeat,[1] jam band"
   ],
   "Years active": [
      "1990–present"
   ],
   "Labels": [
      "Mercury, Island, Touchy Pegg, Shanachie, Adrenaline Music"
   ],
   "Website": [
      "RustedRoot.com"
   ],
   "Members": [
      "Michael GlabickiPatrick NormanLiz Berlin"
   ],
   "Past members": [
      "Jim DiSpiritoJim DonovanJenn WertzJohn BuynakEthan WinogradPreach FreedomColter HarperJason MillerCory CarusoDirk Miller"
   ]
}